red_connector_semcon/__init__.py
red_connector_semcon/commons/__init__.py
red_connector_semcon/commons/cli_modes.py
red_connector_semcon/commons/helpers.py
red_connector_semcon/commons/schemas.py
red_connector_semcon/semcon/__init__.py
red_connector_semcon/semcon/__main__.py
red_connector_semcon/semcon/main.py
red_connector_semcon/semcon/send_receive_file.py
red_connector_semcon/version.py
red_connector_semcon-3.0.0.dist-info/entry_points.txt
red_connector_semcon-3.0.0.dist-info/LICENSE
red_connector_semcon-3.0.0.dist-info/WHEEL
red_connector_semcon-3.0.0.dist-info/METADATA
red_connector_semcon-3.0.0.dist-info/RECORD
