Metadata-Version: 2.1
Name: red-connector-semcon
Version: 3.0.0
Summary: RED Connector Semcon is part of the Curious Containers project.
Home-page: https://www.curious-containers.cc/
License: AGPL-3.0
Author: Christoph Jansen
Author-email: Christoph.Jansen@htw-berlin.de
Requires-Python: >=3.7,<4.0
Classifier: License :: OSI Approved :: GNU Affero General Public License v3
Classifier: Programming Language :: Python :: 3
Classifier: Programming Language :: Python :: 3.10
Classifier: Programming Language :: Python :: 3.7
Classifier: Programming Language :: Python :: 3.8
Classifier: Programming Language :: Python :: 3.9
Requires-Dist: jsonschema (>=3.0,<4.0)
Requires-Dist: requests (>=2.28,<3.0)
Project-URL: Repository, https://github.com/curious-containers/red-connector-semcon
